polyglotjsonnlp/__init__.py
polyglotjsonnlp/server.py
tests/__init__.py
tests/mocks.py
tests/test_polyglotjsonnlp.py
polyglotjsonnlp-0.2.6.dist-info/LICENSE
polyglotjsonnlp-0.2.6.dist-info/METADATA
polyglotjsonnlp-0.2.6.dist-info/WHEEL
polyglotjsonnlp-0.2.6.dist-info/top_level.txt
polyglotjsonnlp-0.2.6.dist-info/RECORD
