Metadata-Version: 2.1
Name: polyglotjsonnlp
Version: 0.2.6
Summary: The Python Polyglot JSON-NLP package
Home-page: https://github.com/dcavar/Polyglot-JSON-NLP
Author: Damir Cavar, Oren Baldinger, Maanvitha Gongalla, Anurag Kumar, Murali Kammili, Boli Fang
Author-email: damir@cavar.me
License: UNKNOWN
Platform: UNKNOWN
Classifier: Programming Language :: Python :: 3
Classifier: License :: OSI Approved :: Apache Software License
Classifier: Operating System :: OS Independent
Requires-Dist: polyglot (>=16.7.4)
Requires-Dist: pyjsonnlp (>=0.2.5)
